COPYING.txt
LICENSE.txt
MANIFEST.in
README.rst
multiplot.py
setup.py
multiplot.egg-info/PKG-INFO
multiplot.egg-info/SOURCES.txt
multiplot.egg-info/dependency_links.txt
multiplot.egg-info/entry_points.txt
multiplot.egg-info/requires.txt
multiplot.egg-info/top_level.txt