Metadata-Version: 1.1
Name: multiplot
Version: 0.1
Summary: Squeeze multiple image files into one page
Home-page: https://github.com/coldfix/multiplot
Author: Thomas Gläßle
Author-email: t_glaessle@gmx.de
License: Public Domain
Platform: UNKNOWN
Classifier: Development Status :: 3 - Alpha
Classifier: Intended Audience :: End Users/Desktop
Classifier: Operating System :: POSIX :: Linux
Classifier: Programming Language :: Python
Classifier: Topic :: Software Development
Classifier: License :: CC0 1.0 Universal (CC0 1.0) Public Domain Dedication
